pbrx/__init__.py
pbrx/container_images.py
pbrx/siblings.py
pbrx/cmd/__init__.py
pbrx/cmd/main.py
pbrx/tests/__init__.py
pbrx/tests/base.py
pbrx/tests/test_command.py
pbrx/tests/test_pbrx.py
pbrx-0.1.0.dist-info/DESCRIPTION.rst
pbrx-0.1.0.dist-info/METADATA
pbrx-0.1.0.dist-info/RECORD
pbrx-0.1.0.dist-info/WHEEL
pbrx-0.1.0.dist-info/entry_points.txt
pbrx-0.1.0.dist-info/metadata.json
pbrx-0.1.0.dist-info/pbr.json
pbrx-0.1.0.dist-info/top_level.txt
